{
	"configurations" : 
	[
		{
			"directories" : 
			[
				{
					"build" : ".",
					"childIndexes" : 
					[
						1,
						8
					],
					"minimumCMakeVersion" : 
					{
						"string" : "3.12"
					},
					"projectIndex" : 0,
					"source" : "."
				},
				{
					"build" : "libs",
					"childIndexes" : 
					[
						2,
						3,
						4,
						5
					],
					"minimumCMakeVersion" : 
					{
						"string" : "3.12"
					},
					"parentIndex" : 0,
					"projectIndex" : 0,
					"source" : "libs"
				},
				{
					"build" : "libs/yocto",
					"minimumCMakeVersion" : 
					{
						"string" : "3.12"
					},
					"parentIndex" : 1,
					"projectIndex" : 0,
					"source" : "libs/yocto",
					"targetIndexes" : 
					[
						3
					]
				},
				{
					"build" : "libs/yocto_pathtrace",
					"minimumCMakeVersion" : 
					{
						"string" : "3.12"
					},
					"parentIndex" : 1,
					"projectIndex" : 0,
					"source" : "libs/yocto_pathtrace",
					"targetIndexes" : 
					[
						6
					]
				},
				{
					"build" : "libs/yocto_extension",
					"minimumCMakeVersion" : 
					{
						"string" : "3.12"
					},
					"parentIndex" : 1,
					"projectIndex" : 0,
					"source" : "libs/yocto_extension",
					"targetIndexes" : 
					[
						4
					]
				},
				{
					"build" : "libs/yocto_gui",
					"childIndexes" : 
					[
						6
					],
					"minimumCMakeVersion" : 
					{
						"string" : "3.12"
					},
					"parentIndex" : 1,
					"projectIndex" : 0,
					"source" : "libs/yocto_gui",
					"targetIndexes" : 
					[
						5
					]
				},
				{
					"build" : "libs/yocto_gui/glfw",
					"childIndexes" : 
					[
						7
					],
					"minimumCMakeVersion" : 
					{
						"string" : "3.0"
					},
					"parentIndex" : 5,
					"projectIndex" : 1,
					"source" : "libs/yocto_gui/ext/glfw"
				},
				{
					"build" : "libs/yocto_gui/glfw/src",
					"minimumCMakeVersion" : 
					{
						"string" : "3.0"
					},
					"parentIndex" : 6,
					"projectIndex" : 1,
					"source" : "libs/yocto_gui/ext/glfw/src",
					"targetIndexes" : 
					[
						0
					]
				},
				{
					"build" : "apps",
					"childIndexes" : 
					[
						9,
						10,
						11,
						12
					],
					"minimumCMakeVersion" : 
					{
						"string" : "3.12"
					},
					"parentIndex" : 0,
					"projectIndex" : 0,
					"source" : "apps"
				},
				{
					"build" : "apps/yscenetrace",
					"minimumCMakeVersion" : 
					{
						"string" : "3.12"
					},
					"parentIndex" : 8,
					"projectIndex" : 0,
					"source" : "apps/yscenetrace",
					"targetIndexes" : 
					[
						8
					]
				},
				{
					"build" : "apps/yimagedenoise",
					"minimumCMakeVersion" : 
					{
						"string" : "3.12"
					},
					"parentIndex" : 8,
					"projectIndex" : 0,
					"source" : "apps/yimagedenoise",
					"targetIndexes" : 
					[
						2
					]
				},
				{
					"build" : "apps/prova",
					"minimumCMakeVersion" : 
					{
						"string" : "3.12"
					},
					"parentIndex" : 8,
					"projectIndex" : 0,
					"source" : "apps/prova",
					"targetIndexes" : 
					[
						1
					]
				},
				{
					"build" : "apps/ysceneitraces",
					"minimumCMakeVersion" : 
					{
						"string" : "3.12"
					},
					"parentIndex" : 8,
					"projectIndex" : 0,
					"source" : "apps/ysceneitraces",
					"targetIndexes" : 
					[
						7
					]
				}
			],
			"name" : "Release",
			"projects" : 
			[
				{
					"childIndexes" : 
					[
						1
					],
					"directoryIndexes" : 
					[
						0,
						1,
						2,
						3,
						4,
						5,
						8,
						9,
						10,
						11,
						12
					],
					"name" : "yocto_pathextension",
					"targetIndexes" : 
					[
						1,
						2,
						3,
						4,
						5,
						6,
						7,
						8
					]
				},
				{
					"directoryIndexes" : 
					[
						6,
						7
					],
					"name" : "GLFW",
					"parentIndex" : 0,
					"targetIndexes" : 
					[
						0
					]
				}
			],
			"targets" : 
			[
				{
					"directoryIndex" : 7,
					"id" : "glfw::@cb216bb1206c33f1f0dc",
					"jsonFile" : "target-glfw-Release-9e03a3adb5798b0e9eae.json",
					"name" : "glfw",
					"projectIndex" : 1
				},
				{
					"directoryIndex" : 11,
					"id" : "prova::@166e960133341d863311",
					"jsonFile" : "target-prova-Release-700acb5ff1264214cf5e.json",
					"name" : "prova",
					"projectIndex" : 0
				},
				{
					"directoryIndex" : 10,
					"id" : "yimagedenoise::@7e486829e6632a046ee3",
					"jsonFile" : "target-yimagedenoise-Release-c9e2a2560052cc38b543.json",
					"name" : "yimagedenoise",
					"projectIndex" : 0
				},
				{
					"directoryIndex" : 2,
					"id" : "yocto::@e229a39159fb9a4cdeaa",
					"jsonFile" : "target-yocto-Release-7392a1fd2d52a54f522d.json",
					"name" : "yocto",
					"projectIndex" : 0
				},
				{
					"directoryIndex" : 4,
					"id" : "yocto_extension::@259d92ba31e184d59c5a",
					"jsonFile" : "target-yocto_extension-Release-20c3e4834bc57cce7e06.json",
					"name" : "yocto_extension",
					"projectIndex" : 0
				},
				{
					"directoryIndex" : 5,
					"id" : "yocto_gui::@e5da5306e8018ef5ac42",
					"jsonFile" : "target-yocto_gui-Release-afefe87124664eea3f23.json",
					"name" : "yocto_gui",
					"projectIndex" : 0
				},
				{
					"directoryIndex" : 3,
					"id" : "yocto_pathtrace::@45510c61010f0b3d598e",
					"jsonFile" : "target-yocto_pathtrace-Release-8ce0a2ded6e1715067a0.json",
					"name" : "yocto_pathtrace",
					"projectIndex" : 0
				},
				{
					"directoryIndex" : 12,
					"id" : "ysceneitraces::@1c2fb099d6103aa362d8",
					"jsonFile" : "target-ysceneitraces-Release-6841946617ee0a99f477.json",
					"name" : "ysceneitraces",
					"projectIndex" : 0
				},
				{
					"directoryIndex" : 9,
					"id" : "yscenetrace::@f7801da1ccefd319b73d",
					"jsonFile" : "target-yscenetrace-Release-dc53df6d6fbc06c1de3a.json",
					"name" : "yscenetrace",
					"projectIndex" : 0
				}
			]
		}
	],
	"kind" : "codemodel",
	"paths" : 
	{
		"build" : "/home/manuel/Data/Università/Magistrale/ComputerGraphics/homeworks/YoctoImageDenoiser/build",
		"source" : "/home/manuel/Data/Università/Magistrale/ComputerGraphics/homeworks/YoctoImageDenoiser"
	},
	"version" : 
	{
		"major" : 2,
		"minor" : 0
	}
}
